phosadsorption/__init__.py
phosadsorption/phosadsorptionlib/__init__.py
phosadsorption/phosadsorptionlib/model.py
phosadsorption/phosadsorptionlib/multioutput_xgb_model.json
phosadsorption/phosadsorptionlib/utils.py
phosadsorption/visuals/__init__.py
phosadsorption/visuals/plot.py
phosadsorption-0.2.8.dist-info/METADATA
phosadsorption-0.2.8.dist-info/WHEEL
phosadsorption-0.2.8.dist-info/top_level.txt
phosadsorption-0.2.8.dist-info/RECORD
