Metadata-Version: 2.4
Name: phosadsorption
Version: 0.2.8
Summary: Phosphorus adsorption modeling in soils
Author-email: Miltiadis Iatrou <m.iatrou@hotmail.gr>
License: MIT
Project-URL: Homepage, https://github.com/Mil-afk/soil_phosphorus_adsorption_data
Project-URL: Repository, https://github.com/Mil-afk/soil_phosphorus_adsorption_data
Project-URL: Issues, https://github.com/Mil-afk/soil_phosphorus_adsorption_data/issues
Classifier: Development Status :: 3 - Alpha
Classifier: Intended Audience :: Science/Research
Classifier: License :: OSI Approved :: MIT License
Classifier: Programming Language :: Python :: 3
Classifier: Programming Language :: Python :: 3.9
Classifier: Operating System :: OS Independent
Requires-Python: >=3.9
